jpstat/__init__.py
jpstat/config.py
jpstat/estat/__init__.py
jpstat/estat/api.py
jpstat/estat/core.py
jpstat/estat/menu.py
jpstat/estat/util/__init__.py
jpstat/estat/util/clean.py
jpstat/estat/util/validate.py
jpstat/estatFile/__init__.py
jpstat/estatFile/core.py
jpstat/estatFile/scrape.py
jpstat/util/__init__.py
jpstat/util/download.py
jpstat/util/io.py
jpstat/util/z2h.py
jpstat/version.py
jpstat-0.0.5.dist-info/LICENSE
jpstat-0.0.5.dist-info/WHEEL
jpstat-0.0.5.dist-info/METADATA
jpstat-0.0.5.dist-info/RECORD
