Metadata-Version: 2.1
Name: jpstat
Version: 0.0.5
Summary: A python library for accessing official statistics of Japan.
Home-page: https://github.com/alalalalaki/jpstat
License: MIT
Keywords: estat,japan,statistics,economics,data
Author: Xuanli Zhu
Author-email: akaguro.koyomi@gmail.com
Requires-Python: >=3.7,<4.0
Classifier: License :: OSI Approved :: MIT License
Classifier: Programming Language :: Python :: 3
Classifier: Programming Language :: Python :: 3.7
Classifier: Programming Language :: Python :: 3.8
Requires-Dist: pandas (>=1.0,<2.0)
Requires-Dist: requests (>=2.0,<3.0)
Requires-Dist: requests_html (>=0.10.0,<0.11.0)
Project-URL: Repository, https://github.com/alalalalaki/jpstat
